comply/__init__.py
comply/__version__.py
comply/main.py
comply/test.py
comply/complyLocal/__init__.py
comply/complyLocal/comply_.py
comply/complyLocal/tests_main.py
comply/complyLocal/tests/__init__.py
comply/complyLocal/tests/test_comply.py
comply-0.0.2.dist-info/METADATA
comply-0.0.2.dist-info/WHEEL
comply-0.0.2.dist-info/top_level.txt
comply-0.0.2.dist-info/RECORD
