Metadata-Version: 2.1
Name: comply
Version: 0.0.2
Summary: Provides functions to check your package's users's python version and shows message to your users continues or stops or accepts callbacks depending your choice.
Home-page: 
Author: Sermet Pekin
Author-email: sermet.pekin@gmail.com
License: MIT
Project-URL: Homepage, https://github.com/SermetPekin/comply-repo
Project-URL: Documentation, https://github.com/SermetPekin/comply-repo
Keywords: comply
Requires-Python: >=3.7.*, <=3.10.*
Provides-Extra: dev
Provides-Extra: docs
Provides-Extra: testing
